setup.py
eru_reloader.egg-info/PKG-INFO
eru_reloader.egg-info/SOURCES.txt
eru_reloader.egg-info/dependency_links.txt
eru_reloader.egg-info/entry_points.txt
eru_reloader.egg-info/not-zip-safe
eru_reloader.egg-info/requires.txt
eru_reloader.egg-info/top_level.txt
reloader/__init__.py
reloader/config.py
reloader/ensure.py
reloader/main.py
reloader/nginx.py
reloader/openresty.py
reloader/sms.py
reloader/templates/__init__.py