Metadata-Version: 1.0
Name: eru-reloader
Version: 1.2
Summary: A reloader daemon for nginx
Home-page: UNKNOWN
Author: tonic
Author-email: tonic@wolege.ca
License: UNKNOWN
Platform: UNKNOWN
